{
  "skippableComposables": 7,
  "restartableComposables": 11,
  "readonlyComposables": 0,
  "totalComposables": 11,
  "restartGroups": 11,
  "totalGroups": 11,
  "staticArguments": 19,
  "certainArguments": 0,
  "knownStableArguments": 229,
  "knownUnstableArguments": 1,
  "unknownStableArguments": 0,
  "totalArguments": 230,
  "markedStableClasses": 0,
  "inferredStableClasses": 0,
  "inferredUnstableClasses": 0,
  "inferredUncertainClasses": 0,
  "effectivelyStableClasses": 0,
  "totalClasses": 0,
  "memoizedLambdas": 4,
  "singletonLambdas": 0,
  "singletonComposableLambdas": 0,
  "composableLambdas": 0,
  "totalLambdas": 4,
  "featureFlags": {
    "StrongSkipping": true,
    "IntrinsicRemember": true,
    "OptimizeNonSkippingGroups": true,
    "PausableComposition": true
  }
}